arnica/.pylintrc
arnica/__init__.py
arnica/cli.py
arnica/__pycache__/__init__.cpython-311.pyc
arnica/__pycache__/__init__.cpython-314.pyc
arnica/__pycache__/cli.cpython-311.pyc
arnica/phys/__init__.py
arnica/phys/solid_material.py
arnica/phys/thermodyn_properties.py
arnica/phys/wall_thermal_equilibrium.py
arnica/phys/yk_from_phi.py
arnica/phys/__pycache__/__init__.cpython-311.pyc
arnica/phys/__pycache__/solid_material.cpython-311.pyc
arnica/phys/__pycache__/thermodyn_properties.cpython-311.pyc
arnica/phys/__pycache__/wall_thermal_equilibrium.cpython-311.pyc
arnica/phys/__pycache__/yk_from_phi.cpython-311.pyc
arnica/plots/__init__.py
arnica/plots/hoveritems.py
arnica/plots/__pycache__/__init__.cpython-311.pyc
arnica/plots/__pycache__/hoveritems.cpython-311.pyc
arnica/solvers_2d/__pycache__/__init__.cpython-311.pyc
arnica/solvers_2d/__pycache__/boundary.cpython-311.pyc
arnica/solvers_2d/__pycache__/conduction.cpython-311.pyc
arnica/solvers_2d/__pycache__/core_fd.cpython-311.pyc
arnica/solvers_2d/__pycache__/radiation.cpython-311.pyc
arnica/utils/README.md
arnica/utils/__init__.py
arnica/utils/axipointcloud.py
arnica/utils/brokenlines_actions.py
arnica/utils/cloud2cloud.py
arnica/utils/cloud2cloud2.py
arnica/utils/curve_feat_extract.py
arnica/utils/datadict2file.py
arnica/utils/directed_projection.py
arnica/utils/mesh_tool.py
arnica/utils/nparray2xmf.py
arnica/utils/plot_ave_with_interval.py
arnica/utils/plot_quad2tri.py
arnica/utils/plotcsv.py
arnica/utils/sample_curve_from_cloud.py
arnica/utils/show_mat.py
arnica/utils/structarr_io.py
arnica/utils/timer_decorator.py
arnica/utils/unstructured_adjacency.py
arnica/utils/vector_actions.py
arnica/utils/__pycache__/__init__.cpython-311.pyc
arnica/utils/__pycache__/__init__.cpython-314.pyc
arnica/utils/__pycache__/axipointcloud.cpython-311.pyc
arnica/utils/__pycache__/axishell.cpython-311.pyc
arnica/utils/__pycache__/axishell_2.cpython-311.pyc
arnica/utils/__pycache__/brokenlines_actions.cpython-311.pyc
arnica-2.0.1.dist-info/licenses/LICENCE.md
arnica-2.0.1.dist-info/METADATA
arnica-2.0.1.dist-info/WHEEL
arnica-2.0.1.dist-info/entry_points.txt
arnica-2.0.1.dist-info/top_level.txt
arnica-2.0.1.dist-info/RECORD
