Metadata-Version: 2.4
Name: arnica
Version: 2.0.1
Summary: All Recurrent No-brainers In Cerfacs Applications
Author-email: CoopTeam-CERFACS <coop@cerfacs.fr>
License: CeCILL-B FREE SOFTWARE LICENSE AGREEMENT
Project-URL: Homepage, https://gitlab.com/cerfacs/arnica
Project-URL: Documentation, https://arnica.readthedocs.io/en/latest/
Project-URL: Issues, https://gitlab.com/cerfacs/arnica/-/issues
Project-URL: Changelog, https://gitlab.com/cerfacs/arnica/-/blob/master/CHANGELOG.md
Keywords: Tool,CFD, Scientific Computing
Classifier: Programming Language :: Python :: 3.11
Classifier: Programming Language :: Python :: 3.12
Classifier: Programming Language :: Python :: 3.13
Classifier: Topic :: Scientific/Engineering
Requires-Python: >=3.11
License-File: LICENCE.md
Requires-Dist: numpy
Requires-Dist: scipy
Requires-Dist: matplotlib
Requires-Dist: h5py
Requires-Dist: lxml
Requires-Dist: click
Requires-Dist: pandas
Requires-Dist: plotille
Provides-Extra: docs
Requires-Dist: sphinx_rtd_theme; extra == "docs"
Requires-Dist: recommonmark; extra == "docs"
Provides-Extra: tests
Requires-Dist: pytest; extra == "tests"
Requires-Dist: pytest-coverage; extra == "tests"
Requires-Dist: pytest-allclose; extra == "tests"
Dynamic: license-file
